{
  "name": "pauldoom",
  "description": "",
  "json_class": "Chef::Environment",
  "chef_type": "environment",
  "default_attributes": {
    "identity-outboundproxy": {
      "use_dashboard_dynamic_updates": true
    },
    "login_dot_gov": {
      "idp_run_migrations": true,
      "allow_unsafe_migrations": true,
      "idp_sync_static": true,
      "gitlab_url": "gitlab.login.gov",
      "gitlab_config_s3_bucket": "login-gov-production-gitlabconfig-217680906704-us-west-2"
    }
  },
  "override_attributes": {}
}
